djazz_utils/__init__.py
djazz_utils-0.1.0rc1.dist-info/LICENSE
djazz_utils-0.1.0rc1.dist-info/WHEEL
djazz_utils-0.1.0rc1.dist-info/METADATA
djazz_utils-0.1.0rc1.dist-info/RECORD
