Metadata-Version: 2.3
Name: djazz-utils
Version: 0.1.0rc1
Summary: Python Financial Animation Library.
Author-email: "Azat (@azataiot)" <8280770+azataiot@users.noreply.github.com>
Classifier: License :: OSI Approved :: GNU General Public License v3 or later (GPLv3+)
Project-URL: Home, https://azat.cc 
